{
  "filer_info": {
    "full_name": "Hon. Sheri Biggs",
    "filer_type": "Member",
    "state": "SC",
    "district": "03"
  },
  "report_type": {
    "is_initial": true,
    "is_amendment": false,
    "date_of_report_being_amended": null
  },
  "ipo_shares_allocated": false,
  "transactions": [
    {
      "owner_code": "SP",
      "asset_name": "Common Stock (APD)",
      "transaction_type": "Sale",
      "transaction_date": "2025-03-18",
      "notification_date": "2025-08-11",
      "amount_range": "$15,001-$50,000",
      "amount_low": 15001,
      "amount_high": 50000,
      "amount_column": "B"
    },
    {
      "owner_code": "SP",
      "asset_name": "representing eight Ordinary share (BABA)",
      "transaction_type": "Sale",
      "transaction_date": "2025-03-18",
      "notification_date": "2025-08-11",
      "amount_range": "$1,001-$15,000",
      "amount_low": 1001,
      "amount_high": 15000,
      "amount_column": "A"
    },
    {
      "owner_code": "SP",
      "asset_name": "SP Altria Group, Inc. (MO)",
      "transaction_type": "Sale",
      "transaction_date": "2025-03-19",
      "notification_date": "2025-08-11",
      "amount_range": "$1,001-$15,000",
      "amount_low": 1001,
      "amount_high": 15000,
      "amount_column": "A"
    },
    {
      "owner_code": "SP",
      "asset_name": "American Depositary Shares (AMX)",
      "transaction_type": "Sale",
      "transaction_date": "2025-03-18",
      "notification_date": "2025-08-11",
      "amount_range": "$1,001-$15,000",
      "amount_low": 1001,
      "amount_high": 15000,
      "amount_column": "A"
    },
    {
      "owner_code": "SP",
      "asset_name": "ADR representing Shares -H- (AHCHY)",
      "transaction_type": "Sale",
      "transaction_date": "2025-03-18",
      "notification_date": "2025-08-11",
      "amount_range": "$1,001-$15,000",
      "amount_low": 1001,
      "amount_high": 15000,
      "amount_column": "A"
    },
    {
      "owner_code": "SP",
      "asset_name": "SP Apple Inc. - Common Stock (AAPL)",
      "transaction_type": "Sale",
      "transaction_date": "2025-03-18",
      "notification_date": "2025-08-11",
      "amount_range": "$15,001-$50,000",
      "amount_low": 15001,
      "amount_high": 50000,
      "amount_column": "B"
    },
    {
      "owner_code": "SP",
      "asset_name": "American Depositary Shares (ASX)",
      "transaction_type": "Sale",
      "transaction_date": "2025-03-18",
      "notification_date": "2025-08-11",
      "amount_range": "$1,001-$15,000",
      "amount_low": 1001,
      "amount_high": 15000,
      "amount_column": "A"
    },
    {
      "owner_code": "SP",
      "asset_name": "SP ASMPT LIMITED UNSP/ADR (ASMVY)",
      "transaction_type": "Sale",
      "transaction_date": "2025-03-18",
      "notification_date": "2025-08-11",
      "amount_range": "$1,001-$15,000",
      "amount_low": 1001,
      "amount_high": 15000,
      "amount_column": "A"
    },
    {
      "owner_code": "SP",
      "asset_name": "SP Banco Do Brasil SA Sponsored ADR (BDORY)",
      "transaction_type": "Sale",
      "transaction_date": "2025-03-18",
      "notification_date": "2025-08-11",
      "amount_range": "$1,001-$15,000",
      "amount_low": 1001,
      "amount_high": 15000,
      "amount_column": "A"
    },
    {
      "owner_code": "SP",
      "asset_name": "Sponsored ADR (BBSEY)",
      "transaction_type": "Sale",
      "transaction_date": "2025-03-18",
      "notification_date": "2025-08-11",
      "amount_range": "$1,001-$15,000",
      "amount_low": 1001,
      "amount_high": 15000,
      "amount_column": "A"
    },
    {
      "owner_code": "SP",
      "asset_name": "New (BDVSY)",
      "transaction_type": "Sale",
      "transaction_date": "2025-03-18",
      "notification_date": "2025-08-11",
      "amount_range": "$1,001-$15,000",
      "amount_low": 1001,
      "amount_high": 15000,
      "amount_column": "A"
    },
    {
      "owner_code": "SP",
      "asset_name": "SP Cemex, S.A.B. de C.V. Sponsored ADR (CX)",
      "transaction_type": "Sale",
      "transaction_date": "2025-03-18",
      "notification_date": "2025-08-11",
      "amount_range": "$1,001-$15,000",
      "amount_low": 1001,
      "amount_high": 15000,
      "amount_column": "A"
    },
    {
      "owner_code": "SP",
      "asset_name": "SP Charles Schwab Corporation (SCHW)",
      "transaction_type": "Sale",
      "transaction_date": "2025-03-19",
      "notification_date": "2025-08-11",
      "amount_range": "$15,001-$50,000",
      "amount_low": 15001,
      "amount_high": 50000,
      "amount_column": "B"
    },
    {
      "owner_code": "SP",
      "asset_name": "SP Chevron Corporation Common Stock (CVX)",
      "transaction_type": "Sale",
      "transaction_date": "2025-03-18",
      "notification_date": "2025-08-11",
      "amount_range": "$15,001-$50,000",
      "amount_low": 15001,
      "amount_high": 50000,
      "amount_column": "B"
    },
    {
      "owner_code": "SP",
      "asset_name": "shares (CICHY)",
      "transaction_type": "Sale",
      "transaction_date": "2025-03-18",
      "notification_date": "2025-08-11",
      "amount_range": "$1,001-$15,000",
      "amount_low": 1001,
      "amount_high": 15000,
      "amount_column": "A"
    },
    {
      "owner_code": "SP",
      "asset_name": "American Depository Receipt (CIHKY)",
      "transaction_type": "Sale",
      "transaction_date": "2025-03-18",
      "notification_date": "2025-08-11",
      "amount_range": "$1,001-$15,000",
      "amount_low": 1001,
      "amount_high": 15000,
      "amount_column": "A"
    },
    {
      "owner_code": "SP",
      "asset_name": "Common Stock (CINF)",
      "transaction_type": "Sale",
      "transaction_date": "2025-03-18",
      "notification_date": "2025-08-11",
      "amount_range": "$1,001-$15,000",
      "amount_low": 1001,
      "amount_high": 15000,
      "amount_column": "A"
    },
    {
      "owner_code": "SP",
      "asset_name": "SP Cisco Systems, Inc. - Common Stock (CSCO)",
      "transaction_type": "Sale",
      "transaction_date": "2025-03-18",
      "notification_date": "2025-08-11",
      "amount_range": "$15,001-$50,000",
      "amount_low": 15001,
      "amount_high": 50000,
      "amount_column": "B"
    },
    {
      "owner_code": "SP",
      "asset_name": "Common Stock (CMCSA)",
      "transaction_type": "Sale",
      "transaction_date": "2025-03-19",
      "notification_date": "2025-08-11",
      "amount_range": "$1,001-$15,000",
      "amount_low": 1001,
      "amount_high": 15000,
      "amount_column": "A"
    },
    {
      "owner_code": "SP",
      "asset_name": "SP Diageo plc Common Stock (DEO)",
      "transaction_type": "Sale",
      "transaction_date": "2025-03-18",
      "notification_date": "2025-08-11",
      "amount_range": "$1,001-$15,000",
      "amount_low": 1001,
      "amount_high": 15000,
      "amount_column": "A"
    },
    {
      "owner_code": "SP",
      "asset_name": "Stock (D)",
      "transaction_type": "Sale",
      "transaction_date": "2025-03-18",
      "notification_date": "2025-08-11",
      "amount_range": "$15,001-$50,000",
      "amount_low": 15001,
      "amount_high": 50000,
      "amount_column": "B"
    },
    {
      "owner_code": "SP",
      "asset_name": "SP ENGIE BRASIL ENE SA S/ADR (EGIEY)",
      "transaction_type": "Sale",
      "transaction_date": "2025-03-18",
      "notification_date": "2025-08-11",
      "amount_range": "$1,001-$15,000",
      "amount_low": 1001,
      "amount_high": 15000,
      "amount_column": "A"
    },
    {
      "owner_code": "SP",
      "asset_name": "SP Fastenal Company - Common Stock (FAST)",
      "transaction_type": "Sale",
      "transaction_date": "2025-03-19",
      "notification_date": "2025-08-11",
      "amount_range": "$15,001-$50,000",
      "amount_low": 15001,
      "amount_high": 50000,
      "amount_column": "B"
    },
    {
      "owner_code": "SP",
      "asset_name": "Services, Inc. Common Stock (FIS)",
      "transaction_type": "Sale",
      "transaction_date": "2025-03-19",
      "notification_date": "2025-08-11",
      "amount_range": "$15,001-$50,000",
      "amount_low": 15001,
      "amount_high": 50000,
      "amount_column": "B"
    },
    {
      "owner_code": "SP",
      "asset_name": "Prognostics SA Unsponsored ADR (GOFPY)",
      "transaction_type": "Sale",
      "transaction_date": "2025-03-18",
      "notification_date": "2025-08-11",
      "amount_range": "$1,001-$15,000",
      "amount_low": 1001,
      "amount_high": 15000,
      "amount_column": "A"
    },
    {
      "owner_code": "SP",
      "asset_name": "C.V Sponsored ADR (GBOOY)",
      "transaction_type": "Sale",
      "transaction_date": "2025-03-18",
      "notification_date": "2025-08-11",
      "amount_range": "$1,001-$15,000",
      "amount_low": 1001,
      "amount_high": 15000,
      "amount_column": "A"
    },
    {
      "owner_code": "SP",
      "asset_name": "Company Limited Unsponsored ADR (HEGIY)",
      "transaction_type": "Sale",
      "transaction_date": "2025-03-18",
      "notification_date": "2025-08-11",
      "amount_range": "$1,001-$15,000",
      "amount_low": 1001,
      "amount_high": 15000,
      "amount_column": "A"
    },
    {
      "owner_code": "SP",
      "asset_name": "represents two ordinary shares. (HIMX)",
      "transaction_type": "Sale",
      "transaction_date": "2025-03-18",
      "notification_date": "2025-08-11",
      "amount_range": "$1,001-$15,000",
      "amount_low": 1001,
      "amount_high": 15000,
      "amount_column": "A"
    },
    {
      "owner_code": "SP",
      "asset_name": "Shares (INFY)",
      "transaction_type": "Sale",
      "transaction_date": "2025-03-18",
      "notification_date": "2025-08-11",
      "amount_range": "$1,001-$15,000",
      "amount_low": 1001,
      "amount_high": 15000,
      "amount_column": "A"
    },
    {
      "owner_code": "SP",
      "asset_name": "Bitcoin Trust ETF (IBIT)",
      "transaction_type": "Purchase",
      "transaction_date": "2025-07-09",
      "notification_date": "2025-08-20",
      "amount_range": "$100,001-$250,000",
      "amount_low": 100001,
      "amount_high": 250000,
      "amount_column": "D"
    },
    {
      "owner_code": "SP",
      "asset_name": "Shares (JD)",
      "transaction_type": "Sale",
      "transaction_date": "2025-03-18",
      "notification_date": "2025-08-11",
      "amount_range": "$1,001-$15,000",
      "amount_low": 1001,
      "amount_high": 15000,
      "amount_column": "A"
    },
    {
      "owner_code": "SP",
      "asset_name": "SP Johnson & Johnson Common Stock (JNJ)",
      "transaction_type": "Sale",
      "transaction_date": "2025-03-19",
      "notification_date": "2025-08-11",
      "amount_range": "$15,001-$50,000",
      "amount_low": 15001,
      "amount_high": 50000,
      "amount_column": "B"
    },
    {
      "owner_code": "SP",
      "asset_name": "SP KASIKORNBANK PCL UNSP/ADR (KPCPY)",
      "transaction_type": "Sale",
      "transaction_date": "2025-03-18",
      "notification_date": "2025-08-11",
      "amount_range": "$1,001-$15,000",
      "amount_low": 1001,
      "amount_high": 15000,
      "amount_column": "A"
    },
    {
      "owner_code": "SP",
      "asset_name": "SP KB Financial Group Inc (KB)",
      "transaction_type": "Sale",
      "transaction_date": "2025-03-18",
      "notification_date": "2025-08-11",
      "amount_range": "$1,001-$15,000",
      "amount_low": 1001,
      "amount_high": 15000,
      "amount_column": "A"
    },
    {
      "owner_code": "SP",
      "asset_name": "V Sponsored ADR (KCDMY)",
      "transaction_type": "Sale",
      "transaction_date": "2025-03-18",
      "notification_date": "2025-08-11",
      "amount_range": "$1,001-$15,000",
      "amount_low": 1001,
      "amount_high": 15000,
      "amount_column": "A"
    },
    {
      "owner_code": "SP",
      "asset_name": "SP KT Corporation Common Stock (KT)",
      "transaction_type": "Sale",
      "transaction_date": "2025-03-18",
      "notification_date": "2025-08-11",
      "amount_range": "$1,001-$15,000",
      "amount_low": 1001,
      "amount_high": 15000,
      "amount_column": "A"
    },
    {
      "owner_code": "SP",
      "asset_name": "SP Lenovo Group Ltd Sponsored ADR (LNVGY)",
      "transaction_type": "Sale",
      "transaction_date": "2025-03-18",
      "notification_date": "2025-08-11",
      "amount_range": "$1,001-$15,000",
      "amount_low": 1001,
      "amount_high": 15000,
      "amount_column": "A"
    },
    {
      "owner_code": "SP",
      "asset_name": "Unsponsored ADR (LTGHY)",
      "transaction_type": "Sale",
      "transaction_date": "2025-03-18",
      "notification_date": "2025-08-11",
      "amount_range": "$1,001-$15,000",
      "amount_low": 1001,
      "amount_high": 15000,
      "amount_column": "A"
    },
    {
      "owner_code": "SP",
      "asset_name": "Stock (LOW)",
      "transaction_type": "Sale",
      "transaction_date": "2025-03-19",
      "notification_date": "2025-08-11",
      "amount_range": "$15,001-$50,000",
      "amount_low": 15001,
      "amount_high": 50000,
      "amount_column": "B"
    },
    {
      "owner_code": "SP",
      "asset_name": "Stock (MRK)",
      "transaction_type": "Sale",
      "transaction_date": "2025-03-19",
      "notification_date": "2025-08-11",
      "amount_range": "$15,001-$50,000",
      "amount_low": 15001,
      "amount_high": 50000,
      "amount_column": "B"
    },
    {
      "owner_code": "SP",
      "asset_name": "Stock (MSFT)",
      "transaction_type": "Sale",
      "transaction_date": "2025-03-19",
      "notification_date": "2025-08-11",
      "amount_range": "$15,001-$50,000",
      "amount_low": 15001,
      "amount_high": 50000,
      "amount_column": "B"
    },
    {
      "owner_code": "SP",
      "asset_name": "Series A (MGYOY)",
      "transaction_type": "Sale",
      "transaction_date": "2025-03-18",
      "notification_date": "2025-08-11",
      "amount_range": "$1,001-$15,000",
      "amount_low": 1001,
      "amount_high": 15000,
      "amount_column": "A"
    },
    {
      "owner_code": "SP",
      "asset_name": "ADR (NDBKY)",
      "transaction_type": "Sale",
      "transaction_date": "2025-03-18",
      "notification_date": "2025-08-11",
      "amount_range": "$1,001-$15,000",
      "amount_low": 1001,
      "amount_high": 15000,
      "amount_column": "A"
    },
    {
      "owner_code": "SP",
      "asset_name": "SP NESTLE S.A S/ADR (NSRGY)",
      "transaction_type": "Sale",
      "transaction_date": "2025-03-19",
      "notification_date": "2025-08-11",
      "amount_range": "$1,001-$15,000",
      "amount_low": 1001,
      "amount_high": 15000,
      "amount_column": "A"
    },
    {
      "owner_code": "SP",
      "asset_name": "shares (NTES)",
      "transaction_type": "Sale",
      "transaction_date": "2025-03-18",
      "notification_date": "2025-08-11",
      "amount_range": "$1,001-$15,000",
      "amount_low": 1001,
      "amount_high": 15000,
      "amount_column": "A"
    },
    {
      "owner_code": "SP",
      "asset_name": "SP Nintendo Co Ltd ADR (NTDOY)",
      "transaction_type": "Sale",
      "transaction_date": "2025-03-19",
      "notification_date": "2025-08-11",
      "amount_range": "$15,001-$50,000",
      "amount_low": 15001,
      "amount_high": 50000,
      "amount_column": "B"
    },
    {
      "owner_code": "SP",
      "asset_name": "Common Stock (NSC)",
      "transaction_type": "Sale",
      "transaction_date": "2025-03-19",
      "notification_date": "2025-08-11",
      "amount_range": "$15,001-$50,000",
      "amount_low": 15001,
      "amount_high": 50000,
      "amount_column": "B"
    },
    {
      "owner_code": "SP",
      "asset_name": "Common Stock (NOC)",
      "transaction_type": "Sale",
      "transaction_date": "2025-03-19",
      "notification_date": "2025-08-11",
      "amount_range": "$15,001-$50,000",
      "amount_low": 15001,
      "amount_high": 50000,
      "amount_column": "B"
    },
    {
      "owner_code": "SP",
      "asset_name": "SP Paychex, Inc. - Common Stock (PAYX)",
      "transaction_type": "Sale",
      "transaction_date": "2025-03-19",
      "notification_date": "2025-08-11",
      "amount_range": "$15,001-$50,000",
      "amount_low": 15001,
      "amount_high": 50000,
      "amount_column": "B"
    },
    {
      "owner_code": "SP",
      "asset_name": "ADS (PBR)",
      "transaction_type": "Sale",
      "transaction_date": "2025-03-18",
      "notification_date": "2025-08-11",
      "amount_range": "$1,001-$15,000",
      "amount_low": 1001,
      "amount_high": 15000,
      "amount_column": "A"
    },
    {
      "owner_code": "SP",
      "asset_name": "Common Stock (PM)",
      "transaction_type": "Sale",
      "transaction_date": "2025-03-19",
      "notification_date": "2025-08-11",
      "amount_range": "$15,001-$50,000",
      "amount_low": 15001,
      "amount_high": 50000,
      "amount_column": "B"
    },
    {
      "owner_code": "SP",
      "asset_name": "SP Ping An Insurance Co Ltd Shares H (PIAIF)",
      "transaction_type": "Sale",
      "transaction_date": "2025-03-18",
      "notification_date": "2025-08-11",
      "amount_range": "$1,001-$15,000",
      "amount_low": 1001,
      "amount_high": 15000,
      "amount_column": "A"
    },
    {
      "owner_code": "SP",
      "asset_name": "SP Progressive Corporation (PGR)",
      "transaction_type": "Sale",
      "transaction_date": "2025-03-19",
      "notification_date": "2025-08-11",
      "amount_range": "$15,001-$50,000",
      "amount_low": 15001,
      "amount_high": 50000,
      "amount_column": "B"
    },
    {
      "owner_code": "SP",
      "asset_name": "Unsponsored ADR (PTAIY)",
      "transaction_type": "Sale",
      "transaction_date": "2025-03-18",
      "notification_date": "2025-08-11",
      "amount_range": "$1,001-$15,000",
      "amount_low": 1001,
      "amount_high": 15000,
      "amount_column": "A"
    },
    {
      "owner_code": "SP",
      "asset_name": "Unsponsored ADR (PPERY)",
      "transaction_type": "Sale",
      "transaction_date": "2025-03-18",
      "notification_date": "2025-08-11",
      "amount_range": "$1,001-$15,000",
      "amount_low": 1001,
      "amount_high": 15000,
      "amount_column": "A"
    },
    {
      "owner_code": "SP",
      "asset_name": "SP PT Telekomunikasi Indonesia, Tbk (TLK)",
      "transaction_type": "Sale",
      "transaction_date": "2025-03-18",
      "notification_date": "2025-08-11",
      "amount_range": "$1,001-$15,000",
      "amount_low": 1001,
      "amount_high": 15000,
      "amount_column": "A"
    },
    {
      "owner_code": "SP",
      "asset_name": "ADR (PUTKY)",
      "transaction_type": "Sale",
      "transaction_date": "2025-03-18",
      "notification_date": "2025-08-11",
      "amount_range": "$1,001-$15,000",
      "amount_low": 1001,
      "amount_high": 15000,
      "amount_column": "A"
    },
    {
      "owner_code": "SP",
      "asset_name": "SP Sanlam Ltd Sponsored ADR (SLLDY)",
      "transaction_type": "Sale",
      "transaction_date": "2025-03-18",
      "notification_date": "2025-08-11",
      "amount_range": "$1,001-$15,000",
      "amount_low": 1001,
      "amount_high": 15000,
      "amount_column": "A"
    },
    {
      "owner_code": "SP",
      "asset_name": "SP Schlumberger N.V. Common Stock (SLB)",
      "transaction_type": "Sale",
      "transaction_date": "2025-03-18",
      "notification_date": "2025-08-11",
      "amount_range": "$1,001-$15,000",
      "amount_low": 1001,
      "amount_high": 15000,
      "amount_column": "A"
    },
    {
      "owner_code": "SP",
      "asset_name": "American Depositary Shares (SHG)",
      "transaction_type": "Sale",
      "transaction_date": "2025-03-18",
      "notification_date": "2025-08-11",
      "amount_range": "$1,001-$15,000",
      "amount_low": 1001,
      "amount_high": 15000,
      "amount_column": "A"
    },
    {
      "owner_code": "SP",
      "asset_name": "Unsponsored ADR (SHTDY)",
      "transaction_type": "Sale",
      "transaction_date": "2025-03-18",
      "notification_date": "2025-08-11",
      "amount_range": "$1,001-$15,000",
      "amount_low": 1001,
      "amount_high": 15000,
      "amount_column": "A"
    },
    {
      "owner_code": "SP",
      "asset_name": "Common Stock (SQM)",
      "transaction_type": "Sale",
      "transaction_date": "2025-03-18",
      "notification_date": "2025-08-11",
      "amount_range": "$1,001-$15,000",
      "amount_low": 1001,
      "amount_high": 15000,
      "amount_column": "A"
    },
    {
      "owner_code": "SP",
      "asset_name": "Sponsored ADR (SGBLY)",
      "transaction_type": "Sale",
      "transaction_date": "2025-03-18",
      "notification_date": "2025-08-11",
      "amount_range": "$1,001-$15,000",
      "amount_low": 1001,
      "amount_high": 15000,
      "amount_column": "A"
    },
    {
      "owner_code": "SP",
      "asset_name": "Stock (SBUX)",
      "transaction_type": "Sale",
      "transaction_date": "2025-03-19",
      "notification_date": "2025-08-11",
      "amount_range": "$15,001-$50,000",
      "amount_low": 15001,
      "amount_high": 50000,
      "amount_column": "B"
    },
    {
      "owner_code": "SP",
      "asset_name": "Manufacturing Company Ltd. (TSM)",
      "transaction_type": "Sale",
      "transaction_date": "2025-03-18",
      "notification_date": "2025-08-11",
      "amount_range": "$1,001-$15,000",
      "amount_low": 1001,
      "amount_high": 15000,
      "amount_column": "A"
    },
    {
      "owner_code": "SP",
      "asset_name": "SP TE Connectivity plc Ordinary Shares (TEL)",
      "transaction_type": "Sale",
      "transaction_date": "2025-03-19",
      "notification_date": "2025-08-11",
      "amount_range": "$15,001-$50,000",
      "amount_low": 15001,
      "amount_high": 50000,
      "amount_column": "B"
    },
    {
      "owner_code": "SP",
      "asset_name": "SP TENCENT HLDGS UNSP/ADR (TCEHY)",
      "transaction_type": "Sale",
      "transaction_date": "2025-03-18",
      "notification_date": "2025-08-11",
      "amount_range": "$1,001-$15,000",
      "amount_low": 1001,
      "amount_high": 15000,
      "amount_column": "A"
    },
    {
      "owner_code": "SP",
      "asset_name": "Depositary Shares (TX)",
      "transaction_type": "Sale",
      "transaction_date": "2025-03-18",
      "notification_date": "2025-08-11",
      "amount_range": "$1,001-$15,000",
      "amount_low": 1001,
      "amount_high": 15000,
      "amount_column": "A"
    },
    {
      "owner_code": "SP",
      "asset_name": "Common Stock (TXN)",
      "transaction_type": "Sale",
      "transaction_date": "2025-03-19",
      "notification_date": "2025-08-11",
      "amount_range": "$15,001-$50,000",
      "amount_low": 15001,
      "amount_high": 50000,
      "amount_column": "B"
    },
    {
      "owner_code": "SP",
      "asset_name": "Sponsored ADR (TCYMY)",
      "transaction_type": "Sale",
      "transaction_date": "2025-03-18",
      "notification_date": "2025-08-11",
      "amount_range": "$1,001-$15,000",
      "amount_low": 1001,
      "amount_high": 15000,
      "amount_column": "A"
    },
    {
      "owner_code": "SP",
      "asset_name": "Stock (UPS)",
      "transaction_type": "Sale",
      "transaction_date": "2025-03-19",
      "notification_date": "2025-08-11",
      "amount_range": "$1,001-$15,000",
      "amount_low": 1001,
      "amount_high": 15000,
      "amount_column": "A"
    },
    {
      "owner_code": "SP",
      "asset_name": "common share (VALE)",
      "transaction_type": "Sale",
      "transaction_date": "2025-03-18",
      "notification_date": "2025-08-11",
      "amount_range": "$1,001-$15,000",
      "amount_low": 1001,
      "amount_high": 15000,
      "amount_column": "A"
    },
    {
      "owner_code": "SP",
      "asset_name": "SP VIBRA ENERGIA UNSP/ADR (PETRY)",
      "transaction_type": "Sale",
      "transaction_date": "2025-03-18",
      "notification_date": "2025-08-11",
      "amount_range": "$1,001-$15,000",
      "amount_low": 1001,
      "amount_high": 15000,
      "amount_column": "A"
    },
    {
      "owner_code": "SP",
      "asset_name": "SP VODACOM GROUP LTD S/ADR (VDMCY)",
      "transaction_type": "Sale",
      "transaction_date": "2025-03-18",
      "notification_date": "2025-08-11",
      "amount_range": "$1,001-$15,000",
      "amount_low": 1001,
      "amount_high": 15000,
      "amount_column": "A"
    }
  ],
  "filer_notes": [],
  "certification": {
    "filer_certified": true,
    "filer_signature": "Hon. Sheri Biggs",
    "filer_signature_date": "2025-10-05",
    "stock_act_certified": true
  },
  "filing_metadata": {
    "transaction_count": 74
  },
  "extraction_metadata": {
    "method": "code_based",
    "filing_type": "P",
    "extraction_timestamp": "2025-11-30T22:03:58.526010+00:00",
    "text_length": 44542,
    "confidence_score": 1.0,
    "textract_recommended": false
  },
  "confidence_score": 1.0,
  "textract_recommended": false,
  "missing_fields": [],
  "filing_type": "P"
}